pyknp/__init__.py
pyknp/evaluate/__init__.py
pyknp/evaluate/dep.py
pyknp/evaluate/mrph.py
pyknp/evaluate/phrase.py
pyknp/evaluate/scorer.py
pyknp/juman/__init__.py
pyknp/juman/juman.py
pyknp/juman/mlist.py
pyknp/juman/morpheme.py
pyknp/juman/process.py
pyknp/knp/__init__.py
pyknp/knp/blist.py
pyknp/knp/bunsetsu.py
pyknp/knp/drawtree.py
pyknp/knp/features.py
pyknp/knp/knp.py
pyknp/knp/pas.py
pyknp/knp/rel.py
pyknp/knp/syngraph.py
pyknp/knp/tag.py
pyknp/knp/tlist.py
tests/__init__.py
tests/test_main.py
unofficial_pyknp-0.4.2.data/scripts/knp-drawtree
unofficial_pyknp-0.4.2.dist-info/AUTHORS
unofficial_pyknp-0.4.2.dist-info/COPYING
unofficial_pyknp-0.4.2.dist-info/METADATA
unofficial_pyknp-0.4.2.dist-info/WHEEL
unofficial_pyknp-0.4.2.dist-info/top_level.txt
unofficial_pyknp-0.4.2.dist-info/RECORD
