Metadata-Version: 2.1
Name: unofficial-pyknp
Version: 0.4.2
Summary: Python module for JUMAN/KNP.
Home-page: https://github.com/ku-nlp/pyknp
Author: Kurohashi-Kawahara Lab, Kyoto Univ.
Author-email: contact@nlp.ist.i.kyoto-u.ac.jp
Maintainer: Kurohashi-Kawahara Lab, Kyoto Univ.
Maintainer-email: contact@nlp.ist.i.kyoto-u.ac.jp
License: See COPYING
Platform: UNKNOWN
Requires-Dist: six
